ocrscreen/__init__.py
ocrscreen/common.py
ocrscreen/learn.py
ocrscreen/core.cpython-39-x86_64-linux-gnu.so
ocrscreen/test.py
ocrscreen/recognize.py
ocrscreen-0.0.5.dist-info/entry_points.txt
ocrscreen-0.0.5.dist-info/RECORD
ocrscreen-0.0.5.dist-info/METADATA
ocrscreen-0.0.5.dist-info/top_level.txt
ocrscreen-0.0.5.dist-info/LICENSE
ocrscreen-0.0.5.dist-info/WHEEL
