Metadata-Version: 2.1
Name: ocrscreen
Version: 0.0.5
Summary: ocr for recognizing text on computer screen
Home-page: https://github.com/mugiseyebrows/ocrscreen
Author: Stanislav Doronin
Author-email: mugisbrows@gmail.com
License: UNKNOWN
Platform: UNKNOWN
License-File: LICENSE
Requires-Dist: numpy
Requires-Dist: opencv-python
Requires-Dist: Pillow
